heisenberg.py
heisenbergpy-0.0.3.dist-info/METADATA
heisenbergpy-0.0.3.dist-info/WHEEL
heisenbergpy-0.0.3.dist-info/top_level.txt
heisenbergpy-0.0.3.dist-info/RECORD
