Metadata-Version: 2.1
Name: heisenbergpy
Version: 0.0.3
Summary: Python client for HeisenbergDB
Author: Quanta
